Workbook

Sheet Start Here
B2: MONTHLY BUDGET PLANNER
B3: A Simple & Beautiful Way to Organize Your Money
B4: Plan • Track • Save • Grow
B6: Name:
B8: Year:
B10: My financial focus this year:
B12: “Small steps, consistently taken, can create meaningful change.”
B15: HOW TO USE THIS WORKBOOK
B16: 1. Record your expected income.
B17: 2. Plan your essential expenses.
B18: 3. Set savings and financial goals.
B19: 4. Track your actual spending.
... B26: This workbook is a personal organizing tool. It records the numbers you enter and adds them up for you. It does not provide financial, investment, tax or legal advice.

Sheet Year at a Glance
A1: MY YEAR AT A GLANCE
B3: MONTH | C3: INCOME | D3: EXPENSES | E3: SAVINGS | F3: LEFT OVER | G3: NOTES
B4: January | F4: =IF(COUNT(C4:E4)=0,"",C4-D4-E4)
B5: February | F5: =IF(COUNT(C5:E5)=0,"",C5-D5-E5)
B6: March | F6: =IF(COUNT(C6:E6)=0,"",C6-D6-E6)
B7: April | F7: =IF(COUNT(C7:E7)=0,"",C7-D7-E7)
B8: May | F8: =IF(COUNT(C8:E8)=0,"",C8-D8-E8)
B9: June | F9: =IF(COUNT(C9:E9)=0,"",C9-D9-E9)
B10: July | F10: =IF(COUNT(C10:E10)=0,"",C10-D10-E10)
B11: August | F11: =IF(COUNT(C11:E11)=0,"",C11-D11-E11)
B12: September | F12: =IF(COUNT(C12:E12)=0,"",C12-D12-E12)
B13: October | F13: =IF(COUNT(C13:E13)=0,"",C13-D13-E13)
B14: November | F14: =IF(COUNT(C14:E14)=0,"",C14-D14-E14)
B15: December | F15: =IF(COUNT(C15:E15)=0,"",C15-D15-E15)
B16: TOTAL | C16: =SUM(C4:C15) | D16: =SUM(D4:D15) | E16: =SUM(E4:E15) | F16: =SUM(F4:F15)
A18: Totals update automatically as you fill in each month.

Sheet Income
A1: INCOME TRACKER
B3: DATE | C3: INCOME SOURCE | D3: EXPECTED | E3: ACTUAL | F3: NOTES
A20: TOTAL EXPECTED INCOME: | F20: =SUM(D4:D19)
A21: TOTAL ACTUAL INCOME: | F21: =SUM(E4:E19)
A22: DIFFERENCE | F22: =SUM(E4:E19)-SUM(D4:D19)

Sheet Fixed Expenses
A1: FIXED EXPENSES
A2: Example labels are shown in grey — replace or add your own.
B4: EXPENSE | C4: DUE DATE | D4: BUDGETED | E4: ACTUAL | F4: PAID
B5: Rent / Mortgage
B6: Utilities
B7: Internet
B8: Insurance
B9: Subscriptions
B10: Loan Payments
B11: Other
A21: TOTAL BUDGETED | F21: =SUM(D5:D20)
A22: TOTAL ACTUAL | F22: =SUM(E5:E20)

Sheet Variable Expenses
A1: VARIABLE EXPENSES
B3: CATEGORY | C3: BUDGETED | D3: ACTUAL | E3: DIFFERENCE
B4: FOOD | E4: =IF(COUNT(C4:D4)=0,"",C4-D4)
B5: TRANSPORTATION | E5: =IF(COUNT(C5:D5)=0,"",C5-D5)
B6: SHOPPING | E6: =IF(COUNT(C6:D6)=0,"",C6-D6)
B7: ENTERTAINMENT | E7: =IF(COUNT(C7:D7)=0,"",C7-D7)
B8: PERSONAL | E8: =IF(COUNT(C8:D8)=0,"",C8-D8)
B9: OTHER | E9: =IF(COUNT(C9:D9)=0,"",C9-D9)
A10: TOTAL | E10: =SUM(D4:D9)
A12: Difference shows budgeted minus actual. A positive number means you stayed under.

Sheet Monthly Budget
A1: MY MONTHLY BUDGET
B3: CATEGORY | C3: PLANNED | D3: ACTUAL | E3: DIFFERENCE
B4: INCOME | E4: =IF(COUNT(C4:D4)=0,"",C4-D4)
B5: HOUSING | E5: =IF(COUNT(C5:D5)=0,"",C5-D5)
B6: UTILITIES | E6: =IF(COUNT(C6:D6)=0,"",C6-D6)
B7: FOOD | E7: =IF(COUNT(C7:D7)=0,"",C7-D7)
B8: TRANSPORTATION | E8: =IF(COUNT(C8:D8)=0,"",C8-D8)
B9: HEALTH | E9: =IF(COUNT(C9:D9)=0,"",C9-D9)
B10: PERSONAL | E10: =IF(COUNT(C10:D10)=0,"",C10-D10)
B11: ENTERTAINMENT | E11: =IF(COUNT(C11:D11)=0,"",C11-D11)
B12: DEBT | E12: =IF(COUNT(C12:D12)=0,"",C12-D12)
B13: SAVINGS | E13: =IF(COUNT(C13:D13)=0,"",C13-D13)
B14: OTHER | E14: =IF(COUNT(C14:D14)=0,"",C14-D14)
B15: TOTAL | C15: =SUM(C4:C14) | D15: =SUM(D4:D14) | E15: =SUM(E4:E14)
A17: Difference shows planned minus actual for each category.

Sheet Bills
A1: BILL PAYMENT TRACKER
A2: “Mark each bill as you pay it.”
B4: BILL | C4: DUE DATE | D4: AMOUNT | E4: PAID DATE | F4: STATUS
A25: TOTAL BILLS | F25: =SUM(D5:D24)
A26: NUMBER MARKED PAID | F26: =COUNTIF(F5:F24,"Paid")

Sheet Subscriptions
A1: SUBSCRIPTION CHECKUP
A2: “Which subscriptions are genuinely useful to me?”
B4: SUBSCRIPTION | C4: MONTHLY COST | D4: RENEWAL DATE | E4: KEEP / CANCEL | F4: NOTES
A21: TOTAL PER MONTH | F21: =SUM(C5:C20)
A22: TOTAL PER YEAR | F22: =SUM(C5:C20)*12
A23: MONTHLY COST OF THE ONES MARKED KEEP | F23: =SUMIF(E5:E20,"Keep",C5:C20)
A24: MONTHLY SAVING IF YOU CANCEL THE REST | F24: =SUMIF(E5:E20,"Cancel",C5:C20)
A26: “Which ones could I live without?”

Sheet Savings Goals
A1: MY SAVINGS GOALS
B3: GOAL | C3: TARGET AMOUNT | D3: CURRENT SAVINGS | E3: DEADLINE | F3: PROGRESS
F4: =IF(N(C4)=0,"",D4/C4)
F5: =IF(N(C5)=0,"",D5/C5)
F6: =IF(N(C6)=0,"",D6/C6)
F7: =IF(N(C7)=0,"",D7/C7)
F8: =IF(N(C8)=0,"",D8/C8)
F9: =IF(N(C9)=0,"",D9/C9)
A10: TOTAL SAVED TOWARD GOALS | F10: =SUM(D4:D9)
A11: TOTAL STILL TO GO | F11: =MAX(0,SUM(C4:C9)-SUM(D4:D9))
B13: EMERGENCY FUND
B14: My current emergency fund:
B15: My target amount:
B16: My monthly contribution:
B17: Progress toward target: | D17: =IF(N(D15)=0,"",D14/D15)
A19: “Progress is progress, even when the amount feels small.”

Sheet Savings Challenge
A1: MY SAVINGS CHALLENGE
B3: MY 30-DAY TARGET:
B5: DAY | C5: AMOUNT SAVED | D5: TOTAL SAVED | F5: DAY | G5: AMOUNT SAVED | H5: TOTAL SAVED
B6: 1 | D6: =IF(COUNT($C$6:C6)=0,"",SUM($C$6:C6)) | F6: 16 | H6: =IF(COUNT($C$6:$C$20,$G$6:G6)=0,"",SUM($C$6:$C$20)+SUM($G$6:G6))
B7: 2 | D7: =IF(COUNT($C$6:C7)=0,"",SUM($C$6:C7)) | F7: 17 | H7: =IF(COUNT($C$6:$C$20,$G$6:G7)=0,"",SUM($C$6:$C$20)+SUM($G$6:G7))
B8: 3 | D8: =IF(COUNT($C$6:C8)=0,"",SUM($C$6:C8)) | F8: 18 | H8: =IF(COUNT($C$6:$C$20,$G$6:G8)=0,"",SUM($C$6:$C$20)+SUM($G$6:G8))
B9: 4 | D9: =IF(COUNT($C$6:C9)=0,"",SUM($C$6:C9)) | F9: 19 | H9: =IF(COUNT($C$6:$C$20,$G$6:G9)=0,"",SUM($C$6:$C$20)+SUM($G$6:G9))
B10: 5 | D10: =IF(COUNT($C$6:C10)=0,"",SUM($C$6:C10)) | F10: 20 | H10: =IF(COUNT($C$6:$C$20,$G$6:G10)=0,"",SUM($C$6:$C$20)+SUM($G$6:G10))
B11: 6 | D11: =IF(COUNT($C$6:C11)=0,"",SUM($C$6:C11)) | F11: 21 | H11: =IF(COUNT($C$6:$C$20,$G$6:G11)=0,"",SUM($C$6:$C$20)+SUM($G$6:G11))
B12: 7 | D12: =IF(COUNT($C$6:C12)=0,"",SUM($C$6:C12)) | F12: 22 | H12: =IF(COUNT($C$6:$C$20,$G$6:G12)=0,"",SUM($C$6:$C$20)+SUM($G$6:G12))
B13: 8 | D13: =IF(COUNT($C$6:C13)=0,"",SUM($C$6:C13)) | F13: 23 | H13: =IF(COUNT($C$6:$C$20,$G$6:G13)=0,"",SUM($C$6:$C$20)+SUM($G$6:G13))
B14: 9 | D14: =IF(COUNT($C$6:C14)=0,"",SUM($C$6:C14)) | F14: 24 | H14: =IF(COUNT($C$6:$C$20,$G$6:G14)=0,"",SUM($C$6:$C$20)+SUM($G$6:G14))
B15: 10 | D15: =IF(COUNT($C$6:C15)=0,"",SUM($C$6:C15)) | F15: 25 | H15: =IF(COUNT($C$6:$C$20,$G$6:G15)=0,"",SUM($C$6:$C$20)+SUM($G$6:G15))
B16: 11 | D16: =IF(COUNT($C$6:C16)=0,"",SUM($C$6:C16)) | F16: 26 | H16: =IF(COUNT($C$6:$C$20,$G$6:G16)=0,"",SUM($C$6:$C$20)+SUM($G$6:G16))
B17: 12 | D17: =IF(COUNT($C$6:C17)=0,"",SUM($C$6:C17)) | F17: 27 | H17: =IF(COUNT($C$6:$C$20,$G$6:G17)=0,"",SUM($C$6:$C$20)+SUM($G$6:G17))
... B20: 15 | D20: =IF(COUNT($C$6:C20)=0,"",SUM($C$6:C20)) | F20: 30 | H20: =IF(COUNT($C$6:$C$20,$G$6:G20)=0,"",SUM($C$6:$C$20)+SUM($G$6:G20))
A22: TOTAL SAVED OVER 30 DAYS | H22: =SUM(C6:C20)+SUM(G6:G20)
A23: AMOUNT LEFT TO REACH YOUR TARGET | H23: =MAX(0,N(C3)-(SUM(C6:C20)+SUM(G6:G20)))

Sheet Debt
A1: DEBT TRACKER
B3: DEBT | C3: STARTING BALANCE | D3: CURRENT BALANCE | E3: MINIMUM PAYMENT | F3: EXTRA PAYMENT | G3: DUE DATE | H3: PAID OFF SO FAR
H4: =IF(COUNT(C4:D4)<2,"",C4-D4)
H5: =IF(COUNT(C5:D5)<2,"",C5-D5)
H6: =IF(COUNT(C6:D6)<2,"",C6-D6)
H7: =IF(COUNT(C7:D7)<2,"",C7-D7)
H8: =IF(COUNT(C8:D8)<2,"",C8-D8)
H9: =IF(COUNT(C9:D9)<2,"",C9-D9)
H10: =IF(COUNT(C10:D10)<2,"",C10-D10)
H11: =IF(COUNT(C11:D11)<2,"",C11-D11)
H12: =IF(COUNT(C12:D12)<2,"",C12-D12)
H13: =IF(COUNT(C13:D13)<2,"",C13-D13)
H14: =IF(COUNT(C14:D14)<2,"",C14-D14)
H15: =IF(COUNT(C15:D15)<2,"",C15-D15)
A16: TOTAL DEBT: | H16: =SUM(D4:D15)
A17: TOTAL PAID THIS MONTH: | H17: =SUM(E4:E15)+SUM(F4:F15)
A18: TOTAL PAID OFF SO FAR | H18: =SUM(H4:H15)
A20: “Focus on progress, consistency, and a plan that fits your budget.”

Sheet Week 1
A1: WEEK 1 — SPENDING TRACKER
B3: DATE | C3: WHAT I SPENT ON | D3: CATEGORY | E3: AMOUNT | F3: NEED / WANT | G3: NOTES
A26: TOTAL SPENT THIS WEEK | G26: =SUM(E4:E25)
A27: SPENT ON NEEDS | G27: =SUMIF(F4:F25,"Need",E4:E25)
A28: SPENT ON WANTS | G28: =SUMIF(F4:F25,"Want",E4:E25)

Sheet Week 2
A1: WEEK 2 — SPENDING TRACKER
B3: DATE | C3: WHAT I SPENT ON | D3: CATEGORY | E3: AMOUNT | F3: NEED / WANT | G3: NOTES
A26: TOTAL SPENT THIS WEEK | G26: =SUM(E4:E25)
A27: SPENT ON NEEDS | G27: =SUMIF(F4:F25,"Need",E4:E25)
A28: SPENT ON WANTS | G28: =SUMIF(F4:F25,"Want",E4:E25)

Sheet Week 3
A1: WEEK 3 — SPENDING TRACKER
B3: DATE | C3: WHAT I SPENT ON | D3: CATEGORY | E3: AMOUNT | F3: NEED / WANT | G3: NOTES
A26: TOTAL SPENT THIS WEEK | G26: =SUM(E4:E25)
A27: SPENT ON NEEDS | G27: =SUMIF(F4:F25,"Need",E4:E25)
A28: SPENT ON WANTS | G28: =SUMIF(F4:F25,"Want",E4:E25)

Sheet Week 4
A1: WEEK 4 — SPENDING TRACKER
B3: DATE | C3: WHAT I SPENT ON | D3: CATEGORY | E3: AMOUNT | F3: NEED / WANT | G3: NOTES
A26: TOTAL SPENT THIS WEEK | G26: =SUM(E4:E25)
A27: SPENT ON NEEDS | G27: =SUMIF(F4:F25,"Need",E4:E25)
A28: SPENT ON WANTS | G28: =SUMIF(F4:F25,"Want",E4:E25)

Sheet Where It Went
A1: WHERE DID MY MONEY GO?
A2: Weekly totals flow in automatically from the Week tabs.
A4: TOTAL SPENT ACROSS WEEKS 1-4 | E4: =N('Week 1'!G26)+N('Week 2'!G26)+N('Week 3'!G26)+N('Week 4'!G26)
B6: CATEGORY | C6: AMOUNT | D6: PERCENTAGE
B7: Housing | D7: =IF(SUM($C$7:$C$15)=0,"",C7/SUM($C$7:$C$15))
B8: Food | D8: =IF(SUM($C$7:$C$15)=0,"",C8/SUM($C$7:$C$15))
B9: Transportation | D9: =IF(SUM($C$7:$C$15)=0,"",C9/SUM($C$7:$C$15))
B10: Bills | D10: =IF(SUM($C$7:$C$15)=0,"",C10/SUM($C$7:$C$15))
B11: Personal | D11: =IF(SUM($C$7:$C$15)=0,"",C11/SUM($C$7:$C$15))
B12: Entertainment | D12: =IF(SUM($C$7:$C$15)=0,"",C12/SUM($C$7:$C$15))
B13: Debt | D13: =IF(SUM($C$7:$C$15)=0,"",C13/SUM($C$7:$C$15))
B14: Savings | D14: =IF(SUM($C$7:$C$15)=0,"",C14/SUM($C$7:$C$15))
B15: Other | D15: =IF(SUM($C$7:$C$15)=0,"",C15/SUM($C$7:$C$15))
B16: TOTAL | C16: =SUM(C7:C15) | D16: =IF(SUM(C7:C15)=0,"",1)
A17: LARGEST CATEGORY | E17: =IF(SUM(C7:C15)=0,"",INDEX(B7:B15,MATCH(MAX(C7:C15),C7:C15,0)))

Sheet Dashboard
A1: MY FINANCIAL DASHBOARD
A2: Everything here is calculated from the other tabs.
B4: TOTAL INCOME | C4: =N('Monthly Budget'!D4) | E4: TOTAL EXPENSES | F4: =(SUM('Monthly Budget'!D4:D14)-N('Monthly Budget'!D4))
B7: TOTAL SAVINGS | C7: =N('Monthly Budget'!D13) | E7: TOTAL DEBT PAYMENT | F7: =N('Monthly Budget'!D12)
B10: SAVINGS RATE | C10: =IF(N('Monthly Budget'!D4)=0,"",N('Monthly Budget'!D13)/N('Monthly Budget'!D4)) | E10: MONEY LEFT OVER | F10: =N('Monthly Budget'!D4)-(SUM('Monthly Budget'!D4:D14)-N('Monthly Budget'!D4))
B13: BIGGEST FINANCIAL WIN
B15: MAIN FOCUS FOR NEXT MONTH
B18: “MY MONEY HAS A PLAN.”
B20: What worked well this month?
B21: What didn’t work?
B22: Where did I overspend?
B23: Where did I make progress?
B24: What surprised me?
B25: What will I do differently next month?

Sheet Monthly Reset
A1: MY FINANCIAL RESET
C3: TASK | D3: DONE
B4: 1 | C4: Review my income
B5: 2 | C5: Review my expenses
B6: 3 | C6: Cancel unnecessary subscriptions
B7: 4 | C7: Check upcoming bills
B8: 5 | C8: Update savings goals
B9: 6 | C9: Review debt payments
B10: 7 | C10: Review spending habits
B11: 8 | C11: Set next month’s budget
B12: 9 | C12: Choose one financial priority
B13: 10 | C13: Celebrate my progress
A14: COMPLETED | D14: =COUNTIF(D4:D13,"Done")&" of 10"
A16: “A fresh month is another opportunity to make intentional choices.”
B18: NEXT MONTH’S MONEY PLAN
B19: MY TOP FINANCIAL PRIORITY
B20: MY SAVINGS TARGET
B21: MY SPENDING LIMIT
B22: A BILL I NEED TO PREPARE FOR
B23: A FINANCIAL GOAL I WANT TO WORK TOWARD
B24: ONE MONEY HABIT I WILL PRACTICE
